wizard_whois/__init__.py
wizard_whois/airports.dat
wizard_whois/countries.dat
wizard_whois/countries3.dat
wizard_whois/domaininfo.py
wizard_whois/net.py
wizard_whois/parse.py
wizard_whois/shared.py
wizard_whois/states_au.dat
wizard_whois/states_ca.dat
wizard_whois/states_us.dat
wizard_whois-2.5.9.data/scripts/pwhois
wizard_whois-2.5.9.dist-info/LICENSE.txt
wizard_whois-2.5.9.dist-info/METADATA
wizard_whois-2.5.9.dist-info/WHEEL
wizard_whois-2.5.9.dist-info/top_level.txt
wizard_whois-2.5.9.dist-info/RECORD
