Metadata-Version: 2.1
Name: wizard-whois
Version: 2.5.9
Summary: Module for retrieving and parsing the WHOIS data for a domain. Supports most domains. Fork of pythonwhois-alt and whois_alt as we need quick bug fixes
Home-page: https://gitlab.com/mikeramsey/whois-alt-for-python
Author: Michael Ramsey
Author-email: mike@hackerdise.me
License: MIT
Keywords: whois nic domain
Platform: UNKNOWN
Classifier: Environment :: Web Environment
Classifier: Intended Audience :: Developers
Classifier: Operating System :: OS Independent
Classifier: Programming Language :: Python
Classifier: Programming Language :: Python :: 3
Classifier: Programming Language :: Python :: 3.6
Classifier: Programming Language :: Python :: 3.7
Classifier: Programming Language :: Python :: 3.8
Classifier: Topic :: Internet :: Name Service (DNS)
Provides: wizard_whois
Requires-Dist: argparse
